{"channelName":"Test","channelId":"1234","logo":"http://logo.com/1234.png","day1":[
{"start":"00:00","stop":"03:00","title":"First Show","subtitle":"First","description":"Test for the first show","season":"","episode":"","showicon":"","actor":"Brad Pitt,George Coloney","director":"","producer":"","writer":"","year":"2004","genre":"Action,Crime","rating":"14","country":"USA,UK"},
{"start":"03:00","stop":"06:00","title":"Second Show","subtitle":"Second","description":"Test for the second show","season":"2","episode":"4","showicon":"","actor":"","director":"","producer":"","writer":"","year":"2020","genre":"Sci-Fi","rating":"12","country":"Italy"},
{"start":"06:00","stop":"09:00","title":"Another Show","subtitle":"","description":"","season":"","episode":"","showicon":"","actor":"","director":"","producer":"","writer":"","year":"","genre":"","rating":"","country":""},
{"start":"09:00","stop":"18:00","title":"Very Long Movie","subtitle":"","description":"Very long and boring movie","season":"","episode":"","showicon":"","actor":"","director":"","producer":"","writer":"","year":"2006","genre":"Drama","rating":"16","country":""},
{"start":"18:00","stop":"00:00","title":"One Another Show","subtitle":"","description":"","season":"","episode":"","showicon":"","actor":"","director":"","producer":"","writer":"","year":"","genre":"","rating":"","country":""}
],"channelId":"1234","day2":[
{"start":"00:00","stop":"03:00","title":"First Show","subtitle":"First","description":"Test for the first show","season":"","episode":"","showicon":"","actor":"Brad Pitt,George Coloney","director":"","producer":"","writer":"","year":"2004","genre":"Action,Crime","rating":"14","country":"USA,UK"},
{"start":"03:00","stop":"06:00","title":"Second Show","subtitle":"Second","description":"Test for the second show","season":"2","episode":"4","showicon":"","actor":"","director":"","producer":"","writer":"","year":"2020","genre":"Sci-Fi","rating":"12","country":"Italy"},
{"start":"06:00","stop":"09:00","title":"Another Show","subtitle":"","description":"","season":"","episode":"","showicon":"","actor":"","director":"","producer":"","writer":"","year":"","genre":"","rating":"","country":""},
{"start":"09:00","stop":"18:00","title":"Very Long Movie","subtitle":"","description":"Very long and boring movie","season":"","episode":"","showicon":"","actor":"","director":"","producer":"","writer":"","year":"2006","genre":"Drama","rating":"16","country":""},
{"start":"18:00","stop":"00:00","title":"One Another Show","subtitle":"","description":"","season":"","episode":"","showicon":"","actor":"","director":"","producer":"","writer":"","year":"","genre":"","rating":"","country":""}
],"channelId":"1234","day3":[
{"start":"00:00","stop":"03:00","title":"First Show","subtitle":"First","description":"Test for the first show","season":"","episode":"","showicon":"","actor":"Brad Pitt,George Coloney","director":"","producer":"","writer":"","year":"2004","genre":"Action,Crime","rating":"14","country":"USA,UK"},
{"start":"03:00","stop":"06:00","title":"Second Show","subtitle":"Second","description":"Test for the second show","season":"2","episode":"4","showicon":"","actor":"","director":"","producer":"","writer":"","year":"2020","genre":"Sci-Fi","rating":"12","country":"Italy"},
{"start":"06:00","stop":"09:00","title":"Another Show","subtitle":"","description":"","season":"","episode":"","showicon":"","actor":"","director":"","producer":"","writer":"","year":"","genre":"","rating":"","country":""},
{"start":"09:00","stop":"18:00","title":"Very Long Movie","subtitle":"","description":"Very long and boring movie","season":"","episode":"","showicon":"","actor":"","director":"","producer":"","writer":"","year":"2006","genre":"Drama","rating":"16","country":""},
{"start":"18:00","stop":"00:00","title":"One Another Show","subtitle":"","description":"","season":"","episode":"","showicon":"","actor":"","director":"","producer":"","writer":"","year":"","genre":"","rating":"","country":""}
],"channelId":"1234","day4":[
{"start":"00:00","stop":"03:00","title":"First Show","subtitle":"First","description":"Test for the first show","season":"","episode":"","showicon":"","actor":"Brad Pitt,George Coloney","director":"","producer":"","writer":"","year":"2004","genre":"Action,Crime","rating":"14","country":"USA,UK"},
{"start":"03:00","stop":"06:00","title":"Second Show","subtitle":"Second","description":"Test for the second show","season":"2","episode":"4","showicon":"","actor":"","director":"","producer":"","writer":"","year":"2020","genre":"Sci-Fi","rating":"12","country":"Italy"},
{"start":"06:00","stop":"09:00","title":"Another Show","subtitle":"","description":"","season":"","episode":"","showicon":"","actor":"","director":"","producer":"","writer":"","year":"","genre":"","rating":"","country":""},
{"start":"09:00","stop":"18:00","title":"Very Long Movie","subtitle":"","description":"Very long and boring movie","season":"","episode":"","showicon":"","actor":"","director":"","producer":"","writer":"","year":"2006","genre":"Drama","rating":"16","country":""},
{"start":"18:00","stop":"00:00","title":"One Another Show","subtitle":"","description":"","season":"","episode":"","showicon":"","actor":"","director":"","producer":"","writer":"","year":"","genre":"","rating":"","country":""}
],"channelId":"1234","day5":[
{"start":"00:00","stop":"03:00","title":"First Show","subtitle":"First","description":"Test for the first show","season":"","episode":"","showicon":"","actor":"Brad Pitt,George Coloney","director":"","producer":"","writer":"","year":"2004","genre":"Action,Crime","rating":"14","country":"USA,UK"},
{"start":"03:00","stop":"06:00","title":"Second Show","subtitle":"Second","description":"Test for the second show","season":"2","episode":"4","showicon":"","actor":"","director":"","producer":"","writer":"","year":"2020","genre":"Sci-Fi","rating":"12","country":"Italy"},
{"start":"06:00","stop":"09:00","title":"Another Show","subtitle":"","description":"","season":"","episode":"","showicon":"","actor":"","director":"","producer":"","writer":"","year":"","genre":"","rating":"","country":""},
{"start":"09:00","stop":"18:00","title":"Very Long Movie","subtitle":"","description":"Very long and boring movie","season":"","episode":"","showicon":"","actor":"","director":"","producer":"","writer":"","year":"2006","genre":"Drama","rating":"16","country":""},
{"start":"18:00","stop":"00:00","title":"One Another Show","subtitle":"","description":"","season":"","episode":"","showicon":"","actor":"","director":"","producer":"","writer":"","year":"","genre":"","rating":"","country":""}
],"channelId":"1234","day6":[
{"start":"00:00","stop":"03:00","title":"First Show","subtitle":"First","description":"Test for the first show","season":"","episode":"","showicon":"","actor":"Brad Pitt,George Coloney","director":"","producer":"","writer":"","year":"2004","genre":"Action,Crime","rating":"14","country":"USA,UK"},
{"start":"03:00","stop":"06:00","title":"Second Show","subtitle":"Second","description":"Test for the second show","season":"2","episode":"4","showicon":"","actor":"","director":"","producer":"","writer":"","year":"2020","genre":"Sci-Fi","rating":"12","country":"Italy"},
{"start":"06:00","stop":"09:00","title":"Another Show","subtitle":"","description":"","season":"","episode":"","showicon":"","actor":"","director":"","producer":"","writer":"","year":"","genre":"","rating":"","country":""},
{"start":"09:00","stop":"18:00","title":"Very Long Movie","subtitle":"","description":"Very long and boring movie","season":"","episode":"","showicon":"","actor":"","director":"","producer":"","writer":"","year":"2006","genre":"Drama","rating":"16","country":""},
{"start":"18:00","stop":"00:00","title":"One Another Show","subtitle":"","description":"","season":"","episode":"","showicon":"","actor":"","director":"","producer":"","writer":"","year":"","genre":"","rating":"","country":""}
],"channelId":"1234","day7":[
{"start":"00:00","stop":"03:00","title":"First Show","subtitle":"First","description":"Test for the first show","season":"","episode":"","showicon":"","actor":"Brad Pitt,George Coloney","director":"","producer":"","writer":"","year":"2004","genre":"Action,Crime","rating":"14","country":"USA,UK"},
{"start":"03:00","stop":"06:00","title":"Second Show","subtitle":"Second","description":"Test for the second show","season":"2","episode":"4","showicon":"","actor":"","director":"","producer":"","writer":"","year":"2020","genre":"Sci-Fi","rating":"12","country":"Italy"},
{"start":"06:00","stop":"09:00","title":"Another Show","subtitle":"","description":"","season":"","episode":"","showicon":"","actor":"","director":"","producer":"","writer":"","year":"","genre":"","rating":"","country":""},
{"start":"09:00","stop":"18:00","title":"Very Long Movie","subtitle":"","description":"Very long and boring movie","season":"","episode":"","showicon":"","actor":"","director":"","producer":"","writer":"","year":"2006","genre":"Drama","rating":"16","country":""},
{"start":"18:00","stop":"00:00","title":"One Another Show","subtitle":"","description":"","season":"","episode":"","showicon":"","actor":"","director":"","producer":"","writer":"","year":"","genre":"","rating":"","country":""}
]}
{"channelName":"Test2","channelId":"3456","logo":"http://logo.com/asdf.png","day1":[
{"start":"00:00","stop":"02:00","title":"Monday Movie","subtitle":"First","description":"Test for the Monday movie","season":"","episode":"","showicon":"","actor":"Brad Pitt,George Coloney","director":"","producer":"","writer":"","year":"2004","genre":"Action,Crime","rating":"14","country":""},
{"start":"02:00","stop":"08:00","title":"Second Movie","subtitle":"Second","description":"Test for the second movie","season":"","episode":"","showicon":"","actor":"","director":"","producer":"","writer":"","year":"2020","genre":"Sci-Fi","rating":"12","country":""},
{"start":"08:00","stop":"12:00","title":"Another Movie","subtitle":"","description":"","season":"","episode":"","showicon":"","actor":"","director":"","producer":"","writer":"","year":"","genre":"","rating":"","country":""},
{"start":"12:00","stop":"19:30","title":"Very Long Movie","subtitle":"","description":"Very long and boring movie","season":"","episode":"","showicon":"","actor":"","director":"","producer":"","writer":"","year":"2006","genre":"Drama","rating":"16","country":""},
{"start":"19:30","stop":"00:00","title":"One Another Movie","subtitle":"","description":"","season":"","episode":"","showicon":"","actor":"","director":"","producer":"","writer":"","year":"","genre":"","rating":"","country":""}
],"channelId":"3456","day2":[
{"start":"00:00","stop":"02:00","title":"First Movie","subtitle":"First","description":"Test for the first movie","season":"","episode":"","showicon":"","actor":"Brad Pitt,George Coloney","director":"","producer":"","writer":"","year":"2004","genre":"Action,Crime","rating":"14","country":""},
{"start":"02:00","stop":"08:00","title":"Second Movie","subtitle":"Second","description":"Test for the second movie","season":"","episode":"","showicon":"","actor":"","director":"","producer":"","writer":"","year":"2020","genre":"Sci-Fi","rating":"12","country":""},
{"start":"08:00","stop":"12:00","title":"Another Movie","subtitle":"","description":"","season":"","episode":"","showicon":"","actor":"","director":"","producer":"","writer":"","year":"","genre":"","rating":"","country":""},
{"start":"12:00","stop":"19:30","title":"Very Long Movie","subtitle":"","description":"Very long and boring movie","season":"","episode":"","showicon":"","actor":"","director":"","producer":"","writer":"","year":"2006","genre":"Drama","rating":"16","country":""},
{"start":"19:30","stop":"00:00","title":"One Another Movie","subtitle":"","description":"","season":"","episode":"","showicon":"","actor":"","director":"","producer":"","writer":"","year":"","genre":"","rating":"","country":""}
],"channelId":"3456","day3":[
{"start":"00:00","stop":"02:00","title":"First Movie","subtitle":"First","description":"Test for the first movie","season":"","episode":"","showicon":"","actor":"Brad Pitt,George Coloney","director":"","producer":"","writer":"","year":"2004","genre":"Action,Crime","rating":"14","country":""},
{"start":"02:00","stop":"08:00","title":"Second Movie","subtitle":"Second","description":"Test for the second movie","season":"","episode":"","showicon":"","actor":"","director":"","producer":"","writer":"","year":"2020","genre":"Sci-Fi","rating":"12","country":""},
{"start":"08:00","stop":"12:00","title":"Another Movie","subtitle":"","description":"","season":"","episode":"","showicon":"","actor":"","director":"","producer":"","writer":"","year":"","genre":"","rating":"","country":""},
{"start":"12:00","stop":"19:30","title":"Very Long Movie","subtitle":"","description":"Very long and boring movie","season":"","episode":"","showicon":"","actor":"","director":"","producer":"","writer":"","year":"2006","genre":"Drama","rating":"16","country":""},
{"start":"19:30","stop":"00:00","title":"One Another Movie","subtitle":"","description":"","season":"","episode":"","showicon":"","actor":"","director":"","producer":"","writer":"","year":"","genre":"","rating":"","country":""}
],"channelId":"3456","day4":[
{"start":"00:00","stop":"02:00","title":"First Movie","subtitle":"First","description":"Test for the first movie","season":"","episode":"","showicon":"","actor":"Brad Pitt,George Coloney","director":"","producer":"","writer":"","year":"2004","genre":"Action,Crime","rating":"14","country":""},
{"start":"02:00","stop":"08:00","title":"Second Movie","subtitle":"Second","description":"Test for the second movie","season":"","episode":"","showicon":"","actor":"","director":"","producer":"","writer":"","year":"2020","genre":"Sci-Fi","rating":"12","country":""},
{"start":"08:00","stop":"12:00","title":"Another Movie","subtitle":"","description":"","season":"","episode":"","showicon":"","actor":"","director":"","producer":"","writer":"","year":"","genre":"","rating":"","country":""},
{"start":"12:00","stop":"19:30","title":"Very Long Movie","subtitle":"","description":"Very long and boring movie","season":"","episode":"","showicon":"","actor":"","director":"","producer":"","writer":"","year":"2006","genre":"Drama","rating":"16","country":""},
{"start":"19:30","stop":"00:00","title":"One Another Movie","subtitle":"","description":"","season":"","episode":"","showicon":"","actor":"","director":"","producer":"","writer":"","year":"","genre":"","rating":"","country":""}
],"channelId":"3456","day5":[
{"start":"00:00","stop":"02:00","title":"First Movie","subtitle":"First","description":"Test for the first movie","season":"","episode":"","showicon":"","actor":"Brad Pitt,George Coloney","director":"","producer":"","writer":"","year":"2004","genre":"Action,Crime","rating":"14","country":""},
{"start":"02:00","stop":"08:00","title":"Second Movie","subtitle":"Second","description":"Test for the second movie","season":"","episode":"","showicon":"","actor":"","director":"","producer":"","writer":"","year":"2020","genre":"Sci-Fi","rating":"12","country":""},
{"start":"08:00","stop":"12:00","title":"Another Movie","subtitle":"","description":"","season":"","episode":"","showicon":"","actor":"","director":"","producer":"","writer":"","year":"","genre":"","rating":"","country":""},
{"start":"12:00","stop":"19:30","title":"Very Long Movie","subtitle":"","description":"Very long and boring movie","season":"","episode":"","showicon":"","actor":"","director":"","producer":"","writer":"","year":"2006","genre":"Drama","rating":"16","country":""},
{"start":"19:30","stop":"00:00","title":"One Another Movie","subtitle":"","description":"","season":"","episode":"","showicon":"","actor":"","director":"","producer":"","writer":"","year":"","genre":"","rating":"","country":""}
],"channelId":"3456","day6":[
{"start":"00:00","stop":"02:00","title":"First Movie","subtitle":"First","description":"Test for the first movie","season":"","episode":"","showicon":"","actor":"Brad Pitt,George Coloney","director":"","producer":"","writer":"","year":"2004","genre":"Action,Crime","rating":"14","country":""},
{"start":"02:00","stop":"08:00","title":"Second Movie","subtitle":"Second","description":"Test for the second movie","season":"","episode":"","showicon":"","actor":"","director":"","producer":"","writer":"","year":"2020","genre":"Sci-Fi","rating":"12","country":""},
{"start":"08:00","stop":"12:00","title":"Another Movie","subtitle":"","description":"","season":"","episode":"","showicon":"","actor":"","director":"","producer":"","writer":"","year":"","genre":"","rating":"","country":""},
{"start":"12:00","stop":"19:30","title":"Very Long Movie","subtitle":"","description":"Very long and boring movie","season":"","episode":"","showicon":"","actor":"","director":"","producer":"","writer":"","year":"2006","genre":"Drama","rating":"16","country":""},
{"start":"19:30","stop":"00:00","title":"One Another Movie","subtitle":"","description":"","season":"","episode":"","showicon":"","actor":"","director":"","producer":"","writer":"","year":"","genre":"","rating":"","country":""}
],"channelId":"3456","day7":[
{"start":"00:00","stop":"02:00","title":"Sunday Movie","subtitle":"First","description":"Test for the first movie","season":"","episode":"","showicon":"","actor":"Brad Pitt,George Coloney","director":"","producer":"","writer":"","year":"2004","genre":"Action,Crime","rating":"14","country":""},
{"start":"02:00","stop":"08:00","title":"Second Movie","subtitle":"Second","description":"Test for the second movie","season":"","episode":"","showicon":"","actor":"","director":"","producer":"","writer":"","year":"2020","genre":"Sci-Fi","rating":"12","country":""},
{"start":"08:00","stop":"12:00","title":"Another Movie","subtitle":"","description":"","season":"","episode":"","showicon":"","actor":"","director":"","producer":"","writer":"","year":"","genre":"","rating":"","country":""},
{"start":"12:00","stop":"19:30","title":"Very Long Movie","subtitle":"","description":"Very long and boring movie","season":"","episode":"","showicon":"","actor":"","director":"","producer":"","writer":"","year":"2006","genre":"Drama","rating":"16","country":""},
{"start":"19:30","stop":"00:00","title":"One Another Movie","subtitle":"","description":"","season":"","episode":"","showicon":"","actor":"","director":"","producer":"","writer":"","year":"","genre":"","rating":"","country":""}
]}